BSCodeTabExtension.py
setup.py
BSCodeTabs.egg-info/PKG-INFO
BSCodeTabs.egg-info/SOURCES.txt
BSCodeTabs.egg-info/dependency_links.txt
BSCodeTabs.egg-info/requires.txt
BSCodeTabs.egg-info/top_level.txt