Metadata-Version: 1.1
Name: BSCodeTabs
Version: 1.0
Summary: Converts Fenced Sequential Blocks in Markdown into Bootstrap HTML Tabs.
Home-page: https://github.com/mikecules/MarkdownBSCodeTabs
Author: Michael Moncada
Author-email: michael.moncada@gmail.com
License: BSD
Platform: Operating System :: OS Independent
Classifier: Intended Audience :: Developers
Classifier: License :: OSI Approved :: BSD License
Classifier: Operating System :: OS Independent
Classifier: Programming Language :: Python
Classifier: Programming Language :: Python :: 2
Classifier: Programming Language :: Python :: 3
Classifier: Topic :: Text Processing
